{
  "id": "eg-law-42-2023",
  "type": "statute",
  "title": "ربط حساب ختامي موازنة جهاز تنظيم مرفق الكهرباء وحماية المستهلك للسنة المالية 2022/2021",
  "short_name": "Law 42/2023",
  "status": "in_force",
  "issued_date": "2023-06-20",
  "in_force_date": "2023-06-20",
  "url": "https://manshurat.org/content/rbt-hsb-khtmy-mwzn-jhz-tnzym-mrfq-lkhrb-whmy-lmsthlk-llsn-lmly-20222021",
  "description": "سياسات اقتصادية ومالية › التجارة والاستثمار والصناعة [PDF: https://manshurat.org/file/88059/download?token=zhqRvcM4]",
  "provisions": [
    {
      "provision_ref": "art1",
      "section": "1",
      "title": "مادة 1",
      "content": "تربط جملة حساب ختامى موازنة جهاز تنظيم مرفق الكهرباء وحماية المستهلك\nللسنة المالية  ٢٠٢٢/٢٠٢١بمبلغ  ١٥٧٠١٠٩٠٢جنيه )فقط وقدره مائة وسبعة\n                      وخمسون مليونﹰا وعشرة آلاف وتسعمائة جنيه واثنان لا غير( ."
    },
    {
      "provision_ref": "art2",
      "section": "2",
      "title": "مادة 2",
      "content": "تربط التكاليف والمصروفات للسنة المالية  ٢٠٢٢/٢٠٢١بمبلغ  ٤٩٢٦٠٩١٨جنيها\n)فقط وقدره تسعة وأربعون مليونﹰا ومائتان وستون ألفﹰا وتسعمائة وثمانية عشر\n                                                   جنيها لا غير( موزعة كالآتى :\n                                            أجور مبلغ  ٢١٦١٥٢٧٣جنيها .\n                        باقى التكاليف والمصروفات مبلغ  ٢٧٦٤٥٦٤٥جنيها ."
    },
    {
      "provision_ref": "art3",
      "section": "3",
      "title": "مادة 3",
      "content": "تربط الإيرادات للسنة المالية  ٢٠٢٢/٢٠٢١بمبلغ  ١١٨٣١٨٩٥٠جنيها\n)فقط وقدره مائة وثمانية عشر مليونﹰا وثلاثمائة وثمانية عشر ألفﹰا وتسعمائة وخمسون\n                                                                جنيها لا غير( ."
    },
    {
      "provision_ref": "art4",
      "section": "4",
      "title": "مادة 4",
      "content": "يربط صافى ربح العام للسنة المالية  ٢٠٢٢/٢٠٢١بمبلغ  ٦٩٠٥٨٠٣٢جنيها\n)فقط وقدره تسعة وستون مليونﹰا وثمانية وخمسون ألفﹰا واثنان وثلاثون جنيها لا غير(\n                                     منه مبلغ  ٥١٧٩٣٥٢٤جنيها فائض حكومة .\n\n٣١     الجريدة الرسمية – العدد  ٢٤مكرر )ھ( فى  ٢٠يونية سنة ٢٠٢٣\n\n                               ) المادة اﳋامسة (\nتربط الاستخدامات الرأسمالية للسنة المالية  ٢٠٢٢/٢٠٢١بمبلغ  ٣٨٦٩١٩٥٢جنيها\n)فقط وقدره ثمانية وثلاثون مليونﹰا وستمائة وواحد وتسعون ألفﹰا وتسعمائة واثنان\n                                           وخمسون جنيها لا غير( موزعة كالآتى :\n                                استخدامات استثمارية مبلغ  ١٣٧٩٩٩٩جنيها .\n                                 تحويلات رأسمالية مبلغ  ٣٧٣١١٩٥٣جنيها ."
    },
    {
      "provision_ref": "art6",
      "section": "6",
      "title": "مادة 6",
      "content": "تربط الإيرادات الرأسمالية للسنة المالية  ٢٠٢٢/٢٠٢١بمبلغ  ٣٨٦٩١٩٥٢جنيها\n)فقط وقدره ثمانية وثلاثون مليونﹰا وستمائة وواحد وتسعون ألفﹰا وتسعمائة واثنان\n                            وخمسون جنيها لا غير( كلها إيرادات رأسمالية متنوعة ."
    },
    {
      "provision_ref": "art7",
      "section": "7",
      "title": "مادة 7",
      "content": "ينشر هذا القانون فى الجريدة الرسمية .\n                     يبصم هذا القانون بخاتم الدولة  ،وينفذ كقانون من قوانينها .\n                             صدر برئاسة الجمهورية فى غرة ذى الحجة سنة  ١٤٤٤ه\n                          ) الموافق  ١٩يونيو سنة  ٢٠٢٣م ( .\nعبد الفتاح السيسي\n\n         الجريدة الرسمية – العدد  ٢٤مكرر )ھ( فى  ٢٠يونية سنة ٢٠٢٣                             ٣٢\n\n                                حساب ختامى موازنة\n                  جهاز تنظيم مرفق الكهرباء وﲪاية المستهلك\n                                 للسنة المالية ٢٠٢٢/٢٠٢١\nالمبالغ بالجنيه\n     ختامى                                          ختامى\n                            الإيرادات                                   التكاليف والمصروفات\n   ٢٠٢٢/٢٠٢١                                       ٢٠٢٢/٢٠٢١\n    ١١٦٫٢٢٣٫١٣٣          مج ) (١إيرادات النشاط         مج ) (١خامات ومواد ووقود وقطع غيار ٧٦٣٫٨٦٩\n\n                                                     ٢١٫٦١٥٫٢٧٣                     مج ) (٢الأجور\n\n        مج ) (٣إيرادات استثمارات وفوائد ٩٤٦٫٥٠٣       ٦٫٥٣٩٫٤٩٦                  مج ) (٣المصروفات\n\n      ١٫١٤٩٫٣١٤       مج ) (٤إيرادات وأرباح أخرى\n\n                                                     ٢٠٫٣٤٢٫٢٨٠              مج ) (٥أعباء وخسائر\n\n    ١١٨٫٣١٨٫٩٥٠          جملة الإيرادات               ٤٩٫٢٦٠٫٩١٨     جملة التكاليف والمصروفات\n\n                                                                                   صافى ربح العام\n\n                                                     ١٧٫٢٦٤٫٥٠٨                       فائض مرحل\n\n                                                     ٥١٫٧٩٣٫٥٢٤                     فائض حكومة\n\n\n\n    ١١٨٫٣١٨٫٩٥٠    جملة ختامى الموازنة الجارية       ١١٨٫٣١٨٫٩٥٠      جملة ختامى الموازنة الجارية\n\n     ٣٨٫٦٩١٫٩٥٢     الإيرادات الرأسمالية المتنوعة       ١٫٣٧٩٫٩٩٩          الاستخدامات الاستثمارية\n\n                                                     ٣٧٫٣١١٫٩٥٣              التحويلات الرأسمالية\n\n     ٣٨٫٦٩١٫٩٥٢     جملة الإيرادات الرأسمالية         ٣٨٫٦٩١٫٩٥٢    جملة الاستخدامات الرأسمالية\n\n    ١٥٧٫٠١٠٫٩٠٢             الإجمالى                ١٥٧٫٠١٠٫٩٠٢              الإجمالى\n\n\n                    \n                                       رئيس مجلس الإدارة\n                          \n                          رقم الإيداع بدار الكتب  ٦٥لسنة ٢٠٢٣\n                          ٧٠٩ - ٢٠٢٣/٧/٥ - ٢٠٢٢/٢٦١٤٨"
    }
  ],
  "definitions": []
}