{
  "id": "eg-law-58-2023",
  "type": "statute",
  "title": "ربط حساب ختامي موازنة وكالة الفضاء المصرية للسنة المالية 2022/2021",
  "short_name": "Law 58/2023",
  "status": "in_force",
  "issued_date": "2023-06-20",
  "in_force_date": "2023-06-20",
  "url": "https://manshurat.org/content/rbt-hsb-khtmy-mwzn-wkl-lfd-lmsry-llsn-lmly-20222021",
  "description": "سياسات اقتصادية ومالية › المالية العامة [PDF: https://manshurat.org/file/88094/download?token=mqYErzp-]",
  "provisions": [
    {
      "provision_ref": "art1",
      "section": "1",
      "title": "مادة 1",
      "content": "تربط جملة حساب ختامى موازنة وكالة الفضاء المصرية للسنة المالية\n ٢٠٢٢/٢٠٢١بمبلغ  ٦٦٣٥١٩٣١٧جنيها )فقط وقدره ستمائة وثلاثة وستون مليونﹰا\n                    وخمسمائة وتسعة عشر ألفﹰا وثلاثمائة وسبعة عشر جنيها لا غير( ."
    },
    {
      "provision_ref": "art2",
      "section": "2",
      "title": "مادة 2",
      "content": "تربط التكاليف والمصروفات للسنة المالية  ٢٠٢٢/٢٠٢١بمبلغ  ٦٨٦٨٠٦٨٦جنيها\n)فقط وقدره ثمانية وستون مليونﹰا وستمائة وثمانون ألفﹰا وستمائة وستة وثمانون\n                                                           جنيها لا غير( موزعة كالآتى :\n                                                    أجور مبلغ  ١٦١٧٦٥٤١جنيها .\n                           باقى التكاليف والمصروفات مبلغ  ٥٢٥٠٤١٤٥جنيها ."
    },
    {
      "provision_ref": "art3",
      "section": "3",
      "title": "مادة 3",
      "content": "ا\n غ  ٢٤٤٢٣٨١جنيه\n                 ة  ٢٠٢٢/٢٠٢١بمبل\n                                  سنة المالي\n                                             رادات لل\n                                                      ربط الإي\n                                                              ت\n      )فقط وقدره مليونان وأربعمائة واثنان وأربعون ألفﹰا وثلاثمائة وواحد وثمانون جنيها لا غير( ."
    },
    {
      "provision_ref": "art4",
      "section": "4",
      "title": "مادة 4",
      "content": "تربط خسائر العام )عجز النشاط( للسنة المالية  ٢٠٢٢/٢٠٢١بمبلغ\n ٦٦٢٣٨٣٠٥جنيهات )فقط وقدره ستة وستون مليونﹰا ومائتان وثمانية وثلاثون ألفﹰا\n                                                      وثلاثمائة وخمسة جنيهات لا غير( .\n\n١٩     الجريدة الرسمية – العدد  ٢٤مكرر )ز( فى  ٢٠يونية سنة ٢٠٢٣\n\n                               ) المادة اﳋامسة (\nتربط الاستخدامات الرأسمالية للسنة المالية  ٢٠٢٢/٢٠٢١بمبلغ  ٥٩٤٨٣٨٦٣١جنيها\n)فقط وقدره خمسمائة وأربعة وتسعون مليونﹰا وثمانمائة وثمانية وثلاثون ألفﹰا وستمائة\n                                     وواحد وثلاثون جنيها لا غير( موزعة كالآتى :\n                             استخدامات استثمارية مبلغ  ٥١٠٠٧٤٧٥٧جنيها .\n                                 تحويلات رأسمالية مبلغ  ٨٤٧٦٣٨٧٤جنيها ."
    },
    {
      "provision_ref": "art6",
      "section": "6",
      "title": "مادة 6",
      "content": "تربط الإيرادات الرأسمالية للسنة المالية  ٢٠٢٢/٢٠٢١بمبلغ  ٥٩٤٨٣٨٦٣١جنيها\n)فقط وقدره خمسمائة وأربعة وتسعون مليونﹰا وثمانمائة وثمانية وثلاثون ألفﹰا وستمائة\nوواحد وثلاثون جنيها لا غير( كلها إيرادات رأسمالية متنوعة منها مساهمة من\nالخزانة العامة بمبلغ  ٥٤٦٠٩٠٤٩١جنيها )لتمويل الاستخدامات الاستثمارية بمبلغ\n       ٤٩٩٩٩٩٧٠٠جنيه ولتمويل التحويلات الرأسمالية بمبلغ  ٤٦٠٩٠٧٩١جنيها( ."
    },
    {
      "provision_ref": "art7",
      "section": "7",
      "title": "مادة 7",
      "content": "ينشر هذا القانون فى الجريدة الرسمية .\n                     يبصم هذا القانون بخاتم الدولة  ،وينفذ كقانون من قوانينها .\n                             صدر برئاسة الجمهورية فى غرة ذى الحجة سنة  ١٤٤٤ه\n                          ) الموافق  ١٩يونيو سنة  ٢٠٢٣م ( .\nعبد الفتاح السيسي\n\n         الجريدة الرسمية – العدد  ٢٤مكرر )ز( فى  ٢٠يونية سنة ٢٠٢٣                             ٢٠\n\n                              حساب ختامى موازنة\n                                  وكالة الفضاء المصرية\n                                للسنة المالية ٢٠٢٢/٢٠٢١\nالمبالغ بالجنيه\n      ختامى                                       ختامى\n                           الإيرادات                                   التكاليف والمصروفات\n    ٢٠٢٢/٢٠٢١                                    ٢٠٢٢/٢٠٢١\n\n         ٦٢١٫٧٧٨        مج ) (١إيرادات النشاط       مج ) (١خامات ومواد ووقود وقطع غيار ٢٫٤٠٨٫٧٨٩\n\n                                                   ١٦٫١٧٦٫٥٤١                      مج ) (٢الأجور\n\n                                                   ٤٨٫٢٠٤٫٣٥١                   مج ) (٣المصروفات\n\n       ١٫٨٢٠٫٦٠٣    مج ) (٤إيرادات وأرباح أخرى\n\n                                                    ١٫٨٩١٫٠٠٥               مج ) (٥أعباء وخسائر\n\n       ٢٫٤٤٢٫٣٨١        جملة الإيرادات              ٦٨٫٦٨٠٫٦٨٦       جملة التكاليف والمصروفات\n\n\n\n\n      خسائر العام ) عجز النشاط ( ٦٦٫٢٣٨٫٣٠٥\n\n\n\n\n      جملة ختامى الموازنة الجارية ٦٨٫٦٨٠٫٦٨٦         ٦٨٫٦٨٠٫٦٨٦      جملة ختامى الموازنة الجارية\n\n     ٥٩٤٫٨٣٨٫٦٣١   الإيرادات الرأسمالية المتنوعة   ٥١٠٫٠٧٤٫٧٥٧            الاستخدامات الاستثمارية\n\n                                                   ٨٤٫٧٦٣٫٨٧٤               التحويلات الرأسمالية\n\n     ٥٩٤٫٨٣٨٫٦٣١   جملة الإيرادات الرأسمالية      ٥٩٤٫٨٣٨٫٦٣١      جملة الاستخدامات الرأسمالية\n\n     ٦٦٣٫٥١٩٫٣١٧           الإجمالى               ٦٦٣٫٥١٩٫٣١٧               الإجمالى"
    }
  ],
  "definitions": []
}